<?xml version="1.0" encoding="UTF-8"?>
<!DOCTYPE struts PUBLIC
	"-//Apache Software Foundation//DTD Struts Configuration 2.3//EN"
	"http://struts.apache.org/dtds/struts-2.3.dtd">
<struts>
	<package name="comment" namespace="/comment" extends="common">
		<action name="commentAction" class="commentAction" >
			<result name="save" type="dispatcher">/pifriend/comment/message.jsp</result>
			<result name="update" type="dispatcher">/pifriend/comment/message.jsp</result>
			<result name="delete" type="dispatcher">/pifriend/comment/message.jsp</result>
			<result name="findById" type="dispatcher">/pifriend/comment/updateComment.jsp</result>
			<result name="findCommentAndReplyByProduct" type="dispatcher">/pifriend/comment/commentList.jsp</result>
		</action>
	</package>
</struts>